Workbook

Sheet Sales
C5: 2026 | D5: 2027 | E5: 2028 | F5: 2029 | G5: 2030 | J5: Assumptions
B6: Sales | C6: 13140.31 | D6: =C10*1.15 -> 16232.357 | E6: =D10*1.15 -> 16419.029 | F6: =E10*1.15 -> 16607.848 | G6: =F10*1.15 -> 16798.838 | J6: EBIT | K6: 150
B7: Total Assets | C7: 13983.69 | D7: =C10 -> 14115.093 | E7: =D10 -> 14277.417 | F7: =E10 -> 14441.607 | G7: =F10 -> 14607.685 | J7: Tax Rate % | K7: 0.27
B8: Capex | C8: =0.04*C6 -> 525.6124 | D8: =0.04*D6 -> 649.29428 | E8: =0.04*E6 -> 656.76117 | F8: =0.04*F6 -> 664.31392 | G8: =0.04*G6 -> 671.95353 | J8: D&A | K8: 3 % of Sales | L8: (Average of the previous years)
B9: D&A | C9: =0.03*C6 -> 394.2093 | D9: =0.03*D6 -> 486.97071 | E9: =0.03*E6 -> 492.57088 | F9: =0.03*F6 -> 498.23544 | G9: =0.03*G6 -> 503.96515 | J9: CapEx | K9: 5% of Sales | L9: (From Concall)
B10: Total Assets For Next Year | C10: =C7+C8-C9 -> 14115.093 | D10: =D7+D8-D9 -> 14277.417 | E10: =E7+E8-E9 -> 14441.607 | F10: =F7+F8-F9 -> 14607.685 | G10: =G7+G8-G9 -> 14775.674 | J10: Non-cash Working Capital | K10: 0.01
J11: Average Assest Turnover | K11: 1.15
J12: Average Interest Growth Rate | K12: 0.17
B14: EBITDA Margins (Conservative) | C14: 0.2 | D14: 0.2 | E14: 0.2 | F14: 0.2 | G14: 0.2
B15: EBITDA Margins (Base) | C15: 0.22 | D15: 0.22 | E15: 0.22 | F15: 0.22 | G15: 0.22
B16: EBITDA Margins (Growth) | C16: 0.25 | D16: 0.25 | E16: 0.25 | F16: 0.25 | G16: 0.25
B19: EBITDA | C19: =C6*C15 -> 2890.8682 | D19: =D6*D15 -> 3571.1186 | E19: =E6*E15 -> 3612.1864 | F19: =F6*F15 -> 3653.7266 | G19: =G6*G15 -> 3695.7444
B20: Working Capital Changes | C20: =0.01*C6 -> 131.4031 | D20: =0.01*D6 -> 162.32357 | E20: =0.01*E6 -> 164.19029 | F20: =0.01*F6 -> 166.07848 | G20: =0.01*G6 -> 167.98838
B21: Interest | C21: =50.35*1.17 -> 58.9095 | D21: =C21*1.17 -> 68.924115 | E21: =D21*1.17 -> 80.641215 | F21: =E21*1.17 -> 94.350221 | G21: =F21*1.17 -> 110.38976
B22: Profit Before Tax | C22: =C19-C9-C21 -> 2437.7494 | D22: =D19-D9-D21 -> 3015.2237 | E22: =E19-E9-E21 -> 3038.9743 | F22: =F19-F9-F21 -> 3061.1409 | G22: =G19-G9-G21 -> 3081.3895
B23: Tax | C23: =0.27*C22 -> 658.19234 | D23: =0.27*D22 -> 814.11041 | E23: =0.27*E22 -> 820.52307 | F23: =0.27*F22 -> 826.50804 | G23: =0.27*G22 -> 831.97517
B25: Free Cash Flow | C25: =C19-C23-C8-C20 -> 1575.6604 | D25: =D19-D23-D8-D20 -> 1945.3903 | E25: =E19-E23-E8-E20 -> 1970.7119 | F25: =F19-F23-F8-F20 -> 1996.8261 | G25: =G19-G23-G8-G20 -> 2023.8273

Sheet Sheet3
A1: COMPANY NAME | B1: PIDILITE INDUSTRIES LTD | E1: =IF(B2<>B3, "A NEW VERSION OF THE WORKSHEET IS AVAILABLE", "")
A2: LATEST VERSION | B2: 2.1 | E2: PLEASE DO NOT MAKE ANY CHANGES TO THIS SHEET
A3: CURRENT VERSION | B3: 2.1
A5: META
A6: Number of shares | B6: =IF(B9>0, B9/B8, 0) -> 101.82404
A7: Face Value | B7: 1
A8: Current Price | B8: 1482.4
A9: Market Capitalization | B9: 150943.96
A15: PROFIT & LOSS
A16: Report Date | B16: 42460 | C16: 42825 | D16: 43190 | E16: 43555 | F16: 43921 | G16: 44286 | H16: 44651 | I16: 45016 | J16: 45382 | K16: 45747
A17: Sales | B17: 5361.17 | C17: 5616.79 | D17: 6078.41 | E17: 7077.96 | F17: 7294.47 | G17: 7292.71 | H17: 9920.96 | I17: 11799.1 | J17: 12382.99 | K17: 13140.31
A18: Raw Material Cost | B18: 2561.41 | C18: 2670.29 | D18: 2883.88 | E18: 3661.79 | F18: 3381.28 | G18: 3494.99 | H18: 5689.14 | I18: 6821.12 | J18: 5867.9 | K18: 6135.04
A19: Change in Inventory | B19: -23.27 | C19: 30.73 | D19: -3.77 | E19: 75.21 | F19: -21.22 | G19: 118.32 | H19: 244.96 | I19: 61.72 | J19: -126.12 | K19: 138.76
A20: % Changes wrt sales | B20: =B19/B17 -> -0.0043404705 | C20: =C19/C17 -> 0.0054710965 | D20: =D19/D17 -> -0.00062022799 | E20: =E19/E17 -> 0.010625943 | F20: =F19/F17 -> -0.002909053 | G20: =G19/G17 -> 0.016224421 | H20: =H19/H17 -> 0.024691159 | I20: =I19/I17 -> 0.0052309074 | ... K20: =K19/K17 -> 0.010559873
A21: Power and Fuel | B21: 48.97 | C21: 53.21 | D21: 59.16 | E21: 66.43 | F21: 67.19 | G21: 68.66 | H21: 87.89 | I21: 97.04 | J21: 106.92 | K21: 113.15
A22: Other Mfr. Exp | B22: 345.8 | C22: 56.83 | D22: 109.42 | E22: 122.97 | F22: 153.27 | G22: 226.5 | H22: 299.49 | I22: 329.87 | J22: 412.83 | K22: 472.32
A23: Employee Cost | B23: 572.46 | C23: 645.62 | D23: 712.88 | E23: 837.13 | F23: 927.66 | G23: 981.91 | H23: 1113.24 | I23: 1246.25 | J23: 1465.97 | K23: 1742.45
A24: Selling and admin | B24: 434.86 | C24: 736.4 | D24: 766.29 | E24: 845.9 | F24: 905.14 | G24: 769.96 | H24: 908.39 | I24: 1142.26 | J24: 1460.42 | K24: 1534.17
A25: Other Expenses | B25: 200.92 | C25: 223.28 | D25: 201.79 | E25: 248.31 | F25: 262.69 | G25: 182.66 | H25: 211.36 | I25: 238.19 | J25: 234.38 | K25: 271.36
A26: Other Income | B26: 81.03 | C26: 115.45 | D26: 153 | E26: 129.79 | F26: 97.27 | G26: 74.03 | H26: 39.06 | I26: 54.53 | J26: 62.75 | K26: 220.95
A27: Depreciation | B27: 100.47 | C27: 115.14 | D27: 119.88 | E27: 132.74 | F27: 169.92 | G27: 200.66 | H27: 239.61 | I27: 269.74 | J27: 340.66 | K27: 358.48
A28: Interest | B28: 13.27 | C28: 13.93 | D28: 15.54 | E28: 26.07 | F28: 33.6 | G28: 37.23 | H28: 42.08 | I28: 47.64 | J28: 51.19 | K28: 50.35
A29: Interest Growth | C29: =(C28-B28)/B28 -> 0.049736247 | D29: =(D28-C28)/C28 -> 0.11557789 | E29: =(E28-D28)/D28 -> 0.67760618 | F29: =(F28-E28)/E28 -> 0.28883774 | G29: =(G28-F28)/F28 -> 0.10803571 | H29: =(H28-G28)/G28 -> 0.13027129 | I29: =(I28-H28)/H28 -> 0.13212928 | J29: =(J28-I28)/I28 -> 0.074517212 | K29: =(K28-J28)/J28 -> -0.016409455
A30: Profit before tax | B30: 1140.77 | C30: 1248.27 | D30: 1358.8 | E30: 1341.62 | F30: 1469.77 | G30: 1522.49 | H30: 1613.78 | I30: 1723.24 | J30: 2379.35 | K30: 2822.7
A31: Tax | B31: 333.54 | C31: 385.05 | D31: 392.71 | E31: 413.23 | F31: 347.72 | G31: 396.36 | H31: 407.02 | I31: 434.37 | J31: 631.93 | K31: 726.53
A32: Tax percent | B32: =B31/B30 -> 0.29238146 | C32: =C31/C30 -> 0.30846692 | D32: =D31/D30 -> 0.28901236 | E32: =E31/E30 -> 0.30800823 | F32: =F31/F30 -> 0.23658123 | G32: =G31/G30 -> 0.26033669 | H32: =H31/H30 -> 0.2522153 | I32: =I31/I30 -> 0.25206588 | ... K32: =K31/K30 -> 0.25738832
A33: Net profit | B33: 802.83 | C33: 859.99 | D33: 962.35 | E33: 924.91 | F33: 1116.42 | G33: 1131.21 | H33: 1207.56 | I33: 1273.25 | J33: 1729.38 | K33: 2076.24
A34: Dividend Amount | B34: 212.77 | C34: 243.53 | D34: 304.68 | E34: 330.2 | F34: 355.67 | G34: 431.97 | H34: 508.3 | I34: 559.13 | J34: 813.76 | K34: 1017.2
G37: Average Tax Rate = | H37: =AVERAGE(B32:K32) -> 0.27220457
G38: Average Interest growth | H38: =AVERAGE(C29:K29) -> 0.1733669
G39: Average Change in
G40: Working capital Wrt Sale | H40: =AVERAGE(B20:K20) -> 0.0054748709
G41: Cost of Debt | H41: =K28/K62 -> 0.1108689
A43: Quarters
A44: Report Date | B44: 45107 | C44: 45199 | D44: 45291 | E44: 45382 | F44: 45473 | G44: 45565 | H44: 45657 | I44: 45747 | J44: 45838 | K44: 45930
A45: Sales | B45: 3275.11 | C45: 3076.04 | D45: 3129.99 | E45: 2901.85 | F45: 3395.35 | G45: 3234.91 | H45: 3368.91 | I45: 3141.14 | J45: 3753.1 | K45: 3554.44
A46: Expenses | B46: 2569.11 | C46: 2397.68 | D46: 2387.54 | E46: 2326.91 | F46: 2583.42 | G46: 2467.32 | H46: 2570.98 | I46: 2509.36 | J46: 2812.12 | K46: 2704.06
A47: Other Income | B47: 23.43 | C47: 31.59 | D47: 37.22 | E47: -22.79 | F47: 53.94 | G47: 57.12 | H47: 55.78 | I47: 55.46 | J47: 85.94 | K47: 50.16
A48: Depreciation | B48: 73.43 | C48: 75.21 | D48: 79.49 | E48: 112.53 | F48: 84.42 | G48: 87.88 | H48: 89.5 | I48: 96.68 | J48: 96.68 | K48: 99.95
A49: Interest | B49: 11.88 | C49: 13.13 | D49: 12.76 | E49: 13.42 | F49: 11.82 | G49: 11.73 | H49: 12.45 | I49: 14.35 | J49: 13.77 | K49: 13.28
A50: Profit before tax | B50: 644.12 | C50: 621.61 | D50: 687.42 | E50: 426.2 | F50: 769.63 | G50: 725.1 | H50: 751.76 | I50: 576.21 | J50: 916.47 | K50: 787.31
A51: Tax | B51: 170.43 | C51: 163.08 | D51: 176.5 | E51: 121.91 | F51: 198.36 | G51: 184.8 | H51: 194.68 | I51: 148.69 | J51: 238.34 | K51: 202.71
A52: Net profit | B52: 468.16 | C52: 450.15 | D52: 510.48 | E52: 300.6 | F52: 566.92 | G52: 534.56 | H52: 552.42 | I52: 422.34 | J52: 672.41 | K52: 579.23
A53: Operating Profit | B53: 706 | C53: 678.36 | D53: 742.45 | E53: 574.94 | F53: 811.93 | G53: 767.59 | H53: 797.93 | I53: 631.78 | J53: 940.98 | K53: 850.38
B54: =B48/B45 -> 0.022420621 | C54: =C48/C45 -> 0.024450267 | D54: =D48/D45 -> 0.025396247 | E54: =E48/E45 -> 0.03877871 | F54: =F48/F45 -> 0.024863416 | G54: =G48/G45 -> 0.027166134 | H54: =H48/H45 -> 0.026566456 | I54: =I48/I45 -> 0.030778635 | ... K54: =K48/K45 -> 0.02811976
D55: Average D&A = | E55: =AVERAGE(B54:K54) -> 0.027430029
A58: BALANCE SHEET
A59: Report Date | B59: 42460 | C59: 42825 | D59: 43190 | E59: 43555 | F59: 43921 | G59: 44286 | H59: 44651 | I59: 45016 | J59: 45382 | K59: 45747
A60: Equity Share Capital | B60: 51.27 | C60: 51.27 | D60: 50.78 | E60: 50.8 | F60: 50.81 | G60: 50.82 | H60: 50.83 | I60: 50.83 | J60: 50.86 | K60: 50.86
A61: Reserves | B61: 2586.72 | C61: 3419.64 | D61: 3523.26 | E61: 4097.29 | F61: 4404.8 | G61: 5542.14 | H61: 6352.88 | I61: 7161.45 | J61: 8356.3 | K61: 9703.6
A62: Borrowings | B62: 80.02 | C62: 97.51 | D62: 124.57 | E62: 112.74 | F62: 287.69 | G62: 331 | H62: 415.83 | I62: 390.61 | J62: 382.47 | K62: 454.14
A63: Other Liabilities | B63: 995.87 | C63: 1202.01 | D63: 1499.99 | E63: 1642.96 | F63: 1779.4 | G63: 2889.87 | H63: 2674.8 | I63: 2901.98 | J63: 3285.98 | K63: 3775.09
A64: Total | B64: 3713.88 | C64: 4770.43 | D64: 5198.6 | E64: 5903.79 | F64: 6522.7 | G64: 8813.83 | H64: 9494.34 | I64: 10504.87 | J64: 12075.61 | K64: 13983.69
A65: Net Block | B65: 1137.46 | C65: 1275.25 | D65: 1342.19 | E65: 1447.61 | F65: 1806.71 | G65: 4417.92 | H65: 4703.26 | I65: 4914.08 | J65: 5450.63 | K65: 5705.29
A66: Capital Work in Progress | B66: 158.07 | C66: 147.71 | D66: 227.73 | E66: 242.13 | F66: 259.33 | G66: 293.87 | H66: 225.42 | I66: 405.94 | J66: 148.09 | K66: 128.95
A67: Investments | B67: 705.54 | C67: 1443.1 | D67: 1245.94 | E67: 1547.7 | F67: 1186.19 | G67: 515.97 | H67: 458.61 | I67: 880.85 | J67: 2235.04 | K67: 3551.32
A68: Other Assets | B68: 1712.81 | C68: 1904.37 | D68: 2382.74 | E68: 2666.35 | F68: 3270.47 | G68: 3586.07 | H68: 4107.05 | I68: 4304 | J68: 4241.85 | K68: 4598.13
A69: Total | B69: 3713.88 | C69: 4770.43 | D69: 5198.6 | E69: 5903.79 | F69: 6522.7 | G69: 8813.83 | H69: 9494.34 | I69: 10504.87 | J69: 12075.61 | K69: 13983.69
A70: Receivables | B70: 701.59 | C70: 768.54 | D70: 938.13 | E70: 1056.01 | F70: 1088.5 | G70: 1321.02 | H70: 1430.54 | I70: 1535.27 | J70: 1674.69 | K70: 1811.15
... A73: No. of Equity Shares | B73: 512675330 | C73: 512682730 | D73: 507810330 | E73: 507978280 | F73: 508123780 | G73: 508153380 | H73: 508288415 | I73: 508314240 | J73: 508609340 | K73: 508648755
A74: New Bonus Shares
A75: Face value | B75: 1 | C75: 1 | D75: 1 | E75: 1 | F75: 1 | G75: 1 | H75: 1 | I75: 1 | J75: 1 | K75: 1
A83: CASH FLOW:
A84: Report Date | B84: 42460 | C84: 42825 | D84: 43190 | E84: 43555 | F84: 43921 | G84: 44286 | H84: 44651 | I84: 45016 | J84: 45382 | K84: 45747
A85: Cash from Operating Activity | B85: 907.47 | C85: 793.75 | D85: 796.43 | E85: 844.78 | F85: 1279.55 | G85: 1392.13 | H85: 955.37 | I85: 1557.57 | J85: 2724.03 | K85: 2286.63
A86: Cash from Investing Activity | B86: -491.14 | C86: -878.97 | D86: 39.26 | E86: -513.14 | F86: 102.94 | G86: -1687.89 | H86: -558.14 | I86: -898.95 | J86: -1769.29 | K86: -1541.59
A87: Cash from Financing Activity | B87: -371.06 | C87: 40.66 | D87: -789.75 | E87: -360.56 | F87: -849.21 | G87: -76.24 | H87: -467.96 | I87: -656.43 | J87: -742.45 | K87: -917.94
A88: Net Cash Flow | B88: 45.27 | C88: -44.56 | D88: 45.94 | E88: -28.92 | F88: 533.28 | G88: -372 | H88: -70.73 | I88: 2.19 | J88: 212.29 | K88: -172.9
A93: PRICE: | B93: 294.65 | C93: 349.58 | D93: 458.9 | E93: 623.13 | F93: 678.2 | G93: 904.7 | H93: 1227.15 | I93: 1176.5 | J93: 1507.35 | K93: 1424.65
A95: DERIVED:
A96: Adjusted Equity Shares in Cr | B96: 102.54 | C96: 102.54 | D96: 101.56 | E96: 101.6 | F96: 101.62 | G96: 101.63 | H96: 101.66 | I96: 101.66 | J96: 101.72 | K96: 101.73
A98: Assest Turnover Ratio | C98: =C17*2/(B69+C69) -> 1.3240417 | D98: =D17*2/(C69+D69) -> 1.2194587 | E98: =E17*2/(D69+E69) -> 1.2750336 | F98: =F17*2/(E69+F69) -> 1.1740194 | G98: =G17*2/(F69+G69) -> 0.95102478 | H98: =H17*2/(G69+H69) -> 1.0837741 | I98: =I17*2/(H69+I69) -> 1.1799566 | J98: =J17*2/(I69+J69) -> 1.0967871 | K98: =K17*2/(J69+K69) -> 1.0084929
G101: =AVERAGE(C98:K98) -> 1.1458432

Sheet WACC
B2: WACC Calculation
B4: Equity value | C4: 150944
B5: Debt value | C5: 454.14
B6: Cost of Debt | C6: 0.11
B7: Tax rate | C7: 0.27
B8: Risk Free Rate | C8: 0.066
B9: Beta | C9: 0.33
B10: Market Return | C10: 0.13
B11: Cost of Equity | C11: =C8+C9*(C10-C8) -> 0.08712
B13: E / D +E | C13: =((C4/(C5+C4)))*C11 -> 0.086858671
B14: D / D+E | C14: =(C5/(C5+C4))*C6*(1-C7) -> 0.00024087114
B15: WACC | C15: =C13+C14 -> 0.087099542

Sheet Terminal Value
B2: Terminal Value Calculation
B4: Assumptions
B5: WACC | C5: =WACC!C15 -> 0.087099542
B6: Growth rate | C6: 0.04
B7: EV/EBITDA Multiple | C7: 43
B9: Period | C9: 0 | D9: 1 | E9: 2 | F9: 3 | G9: 4
B10: EBITDA | D10: 3357.7434 | E10: 3900.019 | F10: 4529.872 | G10: 5261.4464
B11: Free Cash Flow | D11: 1945.3903 | E11: 1970.7119 | F11: 1996.8261 | G11: 2023.8273
G13: Perpertuity Growth TV | H13: =(G11*(1+C6))/(C5-C6) -> 44687.917

Sheet Discounting
B2: Discounting Cash Flows
B4: Assumption
B5: WACC | C5: 0.075
B7: Period | C7: 0 | D7: 1 | E7: 2 | F7: 3 | G7: 4
B8: Free Cash Flow | D8: 1945.3903 | E8: 1970.7119 | F8: 1996.8261 | G8: 2023.8273
B9: Terminal Value | G9: ='Terminal Value'!H13 -> 44687.917
B10: Discount factor | D10: =1/(1+C5)^1 -> 0.93023256 | E10: =1/(1+C5)^2 -> 0.86533261 | F10: =1/(1+C5)^3 -> 0.80496057 | G10: =1/(1+C5)^4 -> 0.74880053
B12: PV of FCF | D12: =D8*D10 -> 1809.6654 | E12: =E8*E10 -> 1705.3213 | F12: =F8*F10 -> 1607.3663 | G12: =G8*G10 -> 1515.443
B13: PV of TV | G13: =G9*G10 -> 33462.336
B15: Enterprise Value | C15: =SUM(D12:G12)+G13 -> 40100.132

Sheet EV to Equity Value
B3: Enterprise Value to Equity Value
B5: Enterprise Value | C5: =Discounting!C15 -> 40100.132
B6: Cash | C6: =Sheet3!K72 -> 336.21
B7: Marketable Securities | C7: =Sheet3!K67 -> 3551.32
B8: Debt | C8: =Sheet3!K62 -> 454.14
B9: Equity Value | C9: =C5+C6+C7-C8 -> 43533.522
B11: Shares Outstanding | C11: 102
B12: Share Price | C12: =C9/C11 -> 426.79923
